stopwords_guilannlp/__init__.py
stopwords_guilannlp/Languages/english.csv
stopwords_guilannlp/Languages/persian.csv
stopwords_guilannlp-13.2019.3.5.dist-info/LICENSE
stopwords_guilannlp-13.2019.3.5.dist-info/METADATA
stopwords_guilannlp-13.2019.3.5.dist-info/WHEEL
stopwords_guilannlp-13.2019.3.5.dist-info/top_level.txt
stopwords_guilannlp-13.2019.3.5.dist-info/RECORD
