Metadata-Version: 2.1
Name: stopwords-guilannlp
Version: 13.2019.3.5
Summary: A comprehensive package for stopwords in NLP and text mining
Home-page: https://github.com/joyebright/stopwords_guilannlp
Author: Javad PourMostafa
Author-email: javad.pourmostafa@gmail.com
License: UNKNOWN
Platform: UNKNOWN
Classifier: Programming Language :: Python :: 3
Classifier: License :: OSI Approved :: MIT License
Classifier: Operating System :: OS Independent
Classifier: Topic :: Text Processing
Classifier: Topic :: Utilities
